AUTHORS
ChangeLog
LICENSE
README.md
setup.cfg
setup.py
bin/event_consumer.py
bin/event_pump.py
bin/pump_from_stv2.py
bin/templategen.py
bin/time_sync.py
notigen/__init__.py
notigen.egg-info/PKG-INFO
notigen.egg-info/SOURCES.txt
notigen.egg-info/dependency_links.txt
notigen.egg-info/not-zip-safe
notigen.egg-info/pbr.json
notigen.egg-info/top_level.txt
templates/compute.instance.create.start_23.json
templates/compute.instance.create.start_24.json
templates/compute.instance.create.start_25.json
templates/compute.instance.create.start_65.json
templates/compute.instance.delete.start_7.json
templates/compute.instance.delete.start_8.json
templates/compute.instance.power_off.start_4.json
templates/compute.instance.power_off.start_5.json
templates/compute.instance.reboot.start_6.json
templates/compute.instance.rebuild.start_14.json
templates/compute.instance.rebuild.start_24.json
templates/compute.instance.rescue.start_19.json
templates/compute.instance.rescue.start_6.json
templates/compute.instance.resize.confirm.start_12.json
templates/compute.instance.resize.confirm.start_4.json
templates/compute.instance.resize.prep.start_24.json
templates/compute.instance.snapshot.start_7.json
templates/compute.instance.snapshot.start_8.json
templates/compute.instance.snapshot.start_9.json
templates/compute.instance.unrescue.start_6.json
templates/eod_exists.json