Metadata-Version: 1.1
Name: notigen
Version: 0.3.dev36
Summary: OpenStack-like notification generator
Home-page: https://github.com/StackTach/notigen
Author: Dark Secret Software Inc.
Author-email: admin@darksecretsoftware.com
License: Apache-2
Keywords: openstack
Platform: UNKNOWN
Classifier: Development Status :: 3 - Alpha
Classifier: Environment :: Console
Classifier: Intended Audience :: Developers
Classifier: Intended Audience :: Information Technology
Classifier: License :: OSI Approved :: Apache Software License
Classifier: Operating System :: OS Independent
Classifier: Programming Language :: Python
Classifier: Topic :: Software Development :: Libraries :: Python Modules
